emm/__init__.py
emm/cli/__init__.py
emm/cli/evg_cli.py
emm/cli/git_cli.py
emm/clients/__init__.py
emm/clients/evg_cli_service.py
emm/clients/evg_service.py
emm/clients/git_proxy.py
emm/clients/github_service.py
emm/emm_cli.py
emm/models/__init__.py
emm/models/repository.py
emm/options.py
emm/services/__init__.py
emm/services/file_service.py
emm/services/git_branch_service.py
emm/services/git_commit_service.py
emm/services/modules_service.py
emm/services/patch_service.py
emm/services/pull_request_service.py
emm/services/validation_service.py
evg_module_manager-1.3.2.dist-info/LICENSE
evg_module_manager-1.3.2.dist-info/METADATA
evg_module_manager-1.3.2.dist-info/WHEEL
evg_module_manager-1.3.2.dist-info/entry_points.txt
evg_module_manager-1.3.2.dist-info/RECORD
