Metadata-Version: 2.1
Name: evg-module-manager
Version: 1.3.2
Summary: Manage Evergreen modules locally.
Home-page: https://github.com/evergreen-ci/evg-module-manager
License: Apache-2.0
Author: Dev Prod DAG
Author-email: dev-prod-dag@mongodb.com
Requires-Python: >=3.7.1,<4.0.0
Classifier: License :: OSI Approved :: Apache Software License
Classifier: Programming Language :: Python :: 3
Classifier: Programming Language :: Python :: 3.8
Classifier: Programming Language :: Python :: 3.9
Classifier: Programming Language :: Python :: 3.10
Classifier: Programming Language :: Python :: 3.11
Requires-Dist: Inject (>=4.3.1,<5.0.0)
Requires-Dist: PyYAML (>=6.0.1,<7.0.0)
Requires-Dist: click (>=8,<9)
Requires-Dist: evergreen.py (>=3.2.7,<4.0.0)
Requires-Dist: plumbum (>=1.7.0,<2.0.0)
Requires-Dist: pydantic (>=1.8.2,<2.0.0)
Requires-Dist: rich (>=10.9.0,<11.0.0)
Requires-Dist: shrub.py (>=3.0.1,<4.0.0)
Requires-Dist: structlog (>=21.1.0,<22.0.0)
Requires-Dist: urllib3 (==1.26.15)
Requires-Dist: xdg (>=5.1.1,<6.0.0)
Project-URL: Documentation, https://evergreen-ci.github.io/evg-module-manager/
Project-URL: Repository, https://github.com/evergreen-ci/evg-module-manager
